pyunit_log/__init__.py
pyunit_log/_log.py
pyunit_log/log.ini
pyunit_log-2020.9.2.dist-info/METADATA
pyunit_log-2020.9.2.dist-info/WHEEL
pyunit_log-2020.9.2.dist-info/top_level.txt
pyunit_log-2020.9.2.dist-info/RECORD
