Metadata-Version: 2.1
Name: pyunit-log
Version: 2020.9.2
Summary: 快速日志模块
Home-page: https://github.com/PyUnit/pyunit-log
Author: Jtyoui
Author-email: jtyoui@qq.com
License: MIT Licence
Platform: any
Classifier: Programming Language :: Python :: 3
Classifier: License :: OSI Approved :: MIT License
Classifier: Operating System :: OS Independent
